mf_toolkit-1.1.1.dist-info/licenses/LICENSE
mftoolkit/MFDFA.py
mftoolkit/__init__.py
mftoolkit/crossovers.py
mftoolkit/mfgeneration.py
mftoolkit/mfsources.py
mftoolkit/test.py
mf_toolkit-1.1.1.dist-info/METADATA
mf_toolkit-1.1.1.dist-info/WHEEL
mf_toolkit-1.1.1.dist-info/top_level.txt
mf_toolkit-1.1.1.dist-info/RECORD
